ixigua/__init__.py
ixigua/version.json
ixigua/bin/__init__.py
ixigua/bin/main.py
ixigua/core/__init__.py
ixigua/core/base.py
ixigua/core/cookies.py
ixigua/core/down.py
ixigua/utils/__init__.py
ixigua/utils/api.py
ixigua/utils/download.py
ixigua/utils/print_item.py
ixigua/utils/url.py
ixigua-1.0.2.dist-info/METADATA
ixigua-1.0.2.dist-info/WHEEL
ixigua-1.0.2.dist-info/entry_points.txt
ixigua-1.0.2.dist-info/top_level.txt
ixigua-1.0.2.dist-info/RECORD
